genice_twist/__init__.py
genice_twist/formats/__init__.py
genice_twist/formats/twist.py
genice_twist-0.1.2.dist-info/METADATA
genice_twist-0.1.2.dist-info/WHEEL
genice_twist-0.1.2.dist-info/entry_points.txt
genice_twist-0.1.2.dist-info/top_level.txt
genice_twist-0.1.2.dist-info/RECORD
