Metadata-Version: 2.1
Name: genice-twist
Version: 0.1.2
Summary: Twist analysis plugin for GenIce.
Home-page: https://github.com/vitroid/genice-twist/
Author: Masakazu Matsumoto
Author-email: vitroid@gmail.com
License: MIT
Keywords: genice,chirality
Platform: UNKNOWN
Classifier: Development Status :: 4 - Beta
Classifier: Intended Audience :: Developers
Classifier: Programming Language :: Python
Classifier: Programming Language :: Python :: 3.5
Requires-Dist: genice (<2.0)
Requires-Dist: genice-svg (>=0.4)
Requires-Dist: twist-op (>=0.2)
Requires-Dist: sklearn
